scratchapi/__init__.py
scratchapi/exceptions.py
scratchapi/project.py
scratchapi/session.py
scratchapi/user.py
scratchapi_python-1.0.1.dist-info/LICENSE
scratchapi_python-1.0.1.dist-info/METADATA
scratchapi_python-1.0.1.dist-info/WHEEL
scratchapi_python-1.0.1.dist-info/top_level.txt
scratchapi_python-1.0.1.dist-info/RECORD
