Metadata-Version: 2.1
Name: scratchapi-python
Version: 1.0.1
Summary: An API for Scratch.
Author: Artcas2
Project-URL: Github, https://github.com/Artcas2/scratchapi-python
Requires-Python: >=3.9
License-File: LICENSE
Requires-Dist: requests
